hevy_api_client/__init__.py
hevy_api_client/client.py
hevy_api_client/errors.py
hevy_api_client/py.typed
hevy_api_client/types.py
hevy_api_client/api/__init__.py
hevy_api_client/api/exercise_templates/__init__.py
hevy_api_client/api/exercise_templates/get_v1_exercise_templates.py
hevy_api_client/api/routine_folders/__init__.py
hevy_api_client/api/routine_folders/get_v1_routine_folders.py
hevy_api_client/api/routine_folders/post_v1_routine_folders.py
hevy_api_client/api/routines/__init__.py
hevy_api_client/api/routines/get_v1_routines.py
hevy_api_client/api/routines/post_v1_routines.py
hevy_api_client/api/workouts/__init__.py
hevy_api_client/api/workouts/get_v1_workouts.py
hevy_api_client/api/workouts/get_v1_workouts_count.py
hevy_api_client/api/workouts/get_v1_workouts_events.py
hevy_api_client/cli/__init__.py
hevy_api_client/cli/exercise_templates.py
hevy_api_client/cli/routine_folders.py
hevy_api_client/cli/routines.py
hevy_api_client/cli/utils.py
hevy_api_client/models/__init__.py
hevy_api_client/models/deleted_workout.py
hevy_api_client/models/exercise_template.py
hevy_api_client/models/get_v1_exercise_templates_response_200.py
hevy_api_client/models/get_v1_routine_folders_response_200.py
hevy_api_client/models/get_v1_routines_response_200.py
hevy_api_client/models/get_v1_workouts_count_response_200.py
hevy_api_client/models/get_v1_workouts_response_200.py
hevy_api_client/models/paginated_workout_events.py
hevy_api_client/models/post_routine_folder_request_body.py
hevy_api_client/models/post_routine_folder_request_body_routine_folder.py
hevy_api_client/models/post_routines_request_body.py
hevy_api_client/models/post_routines_request_body_routine.py
hevy_api_client/models/post_routines_request_exercise.py
hevy_api_client/models/post_routines_request_set.py
hevy_api_client/models/post_routines_request_set_type.py
hevy_api_client/models/post_v1_routine_folders_response_400.py
hevy_api_client/models/post_v1_routines_response_400.py
hevy_api_client-0.1.1.dist-info/METADATA
hevy_api_client-0.1.1.dist-info/WHEEL
hevy_api_client-0.1.1.dist-info/entry_points.txt
hevy_api_client-0.1.1.dist-info/RECORD
