Metadata-Version: 2.4
Name: hevy-api-client
Version: 0.1.1
Summary: A client library to interact with Hevy API + a CLI tool
Project-URL: Source, https://github.com/jorgegomzar/hevy-api-client
Author-email: Jorge Gómez Zarzosa <jorge.gomez@gmail.com>
Requires-Python: >=3.9
Requires-Dist: attrs>=22.2.0
Requires-Dist: httpx<0.29.0,>=0.20.0
Requires-Dist: python-dateutil<3,>=2.8.0
Requires-Dist: typer>=0.15.2
